LICENSE.txt
README.md
setup.cfg
setup.py
developer_basics/developer_basics.py
developer_basics.egg-info/PKG-INFO
developer_basics.egg-info/SOURCES.txt
developer_basics.egg-info/dependency_links.txt
developer_basics.egg-info/top_level.txt