Metadata-Version: 2.1
Name: developer-basics
Version: 0.2
Summary: Contains basic developer helper functions
Home-page: https://github.com/tylerhirsch62/developer-basics
Download-URL: https://github.com/tylerhirsch62/developer-basics/archive/refs/tags/v_0.2.tar.gz
Author: Tyler Hirsch
Author-email: tylerhirschbiz@gmail.com
License: MIT
Keywords: developer,basics,developer_basics
Classifier: Development Status :: 3 - Alpha
Classifier: Intended Audience :: Developers
Classifier: Topic :: Software Development :: Build Tools
Classifier: License :: OSI Approved :: MIT License
Classifier: Programming Language :: Python :: 3
Classifier: Programming Language :: Python :: 3.4
Classifier: Programming Language :: Python :: 3.5
Classifier: Programming Language :: Python :: 3.6
Classifier: Programming Language :: Python :: 3.7
Classifier: Programming Language :: Python :: 3.8
Classifier: Programming Language :: Python :: 3.9
Classifier: Programming Language :: Python :: 3.10
License-File: LICENSE.txt
